brokolisql/cli.py
brokolisql/setup.py
brokolisql/assets/banner.txt
brokolisql/dialects/__init__.py
brokolisql/dialects/base.py
brokolisql/dialects/generic.py
brokolisql/dialects/mysql.py
brokolisql/dialects/oracle.py
brokolisql/dialects/postgres.py
brokolisql/dialects/sqlite.py
brokolisql/dialects/sqlserver.py
brokolisql/exceptions/__init__.py
brokolisql/exceptions/base.py
brokolisql/output/output_writer.py
brokolisql/services/normalizer.py
brokolisql/services/sql_generator.py
brokolisql/services/type_inference.py
brokolisql/transformers/__init__.py
brokolisql/transformers/transform_engine.py
brokolisql/utils/file_loader.py
brokolisql-0.2.0.dist-info/licenses/LICENSE
brokolisql-0.2.0.dist-info/METADATA
brokolisql-0.2.0.dist-info/WHEEL
brokolisql-0.2.0.dist-info/entry_points.txt
brokolisql-0.2.0.dist-info/top_level.txt
brokolisql-0.2.0.dist-info/RECORD
