Metadata-Version: 2.4
Name: brokolisql
Version: 0.2.0
Summary: BrokoliSQL is a Python-based command-line tool designed to facilitate the conversion of structured data files—such as CSV, Excel, JSON, and XML—into SQL INSERT statements. It solves common problems faced during data import, transformation, and database seeding by offering a flexible, extensible, and easy-to-use interface.
Author-email: "Pitch.ai" <pitch.ai@dsai.co.mz>, Abel Eduardo Mondlane <abeleduardohc12@gmail.com>
License: GPL
Keywords: csv,excel,sql,converter,data
Classifier: Programming Language :: Python :: 3
Classifier: License :: OSI Approved :: GNU General Public License v3 (GPLv3)
Classifier: Operating System :: OS Independent
Requires-Python: >=3.7
License-File: LICENSE
Requires-Dist: pandas
Requires-Dist: tqdm
Requires-Dist: openpyxl
Requires-Dist: pyyaml
Requires-Dist: numpy
Dynamic: license-file
